bar.py
uv_study_py-0.1.0.dist-info/METADATA
uv_study_py-0.1.0.dist-info/WHEEL
uv_study_py-0.1.0.dist-info/top_level.txt
uv_study_py-0.1.0.dist-info/RECORD
