Metadata-Version: 2.4
Name: uv-study-py
Version: 0.1.0
Summary: Add your description here
Requires-Python: >=3.13
Requires-Dist: basiclibrary-py>=0.6.55
